SG_Sentence/__init__.py
SG_Sentence/__main__.py
SG_Sentence-1.0.dist-info/LICENCE
SG_Sentence-1.0.dist-info/METADATA
SG_Sentence-1.0.dist-info/WHEEL
SG_Sentence-1.0.dist-info/top_level.txt
SG_Sentence-1.0.dist-info/RECORD
