Metadata-Version: 2.1
Name: SG-Sentence
Version: 1.0
Summary: An Awesome Module to Encode & Decode A String...
Home-page: https://github.com/sancho1952007/SG_Sentence
Author: Sancho Godinho
License: UNKNOWN
Project-URL: Bug Tracker, https://github.com/sancho1952007/SG_Sentence/issues
Keywords: sg_encode,sg_decode
Platform: UNKNOWN
